{
    "id": "https://neuma.huma-num.fr/home/opus/all:airs:timbres:cdc:0383",
    "url": "https://neuma.huma-num.fr/home/opus/all:airs:timbres:cdc:0383",
    "ref": "all:airs:timbres:cdc:0383",
    "local_ref": "0383",
    "collection_ref": "all:airs:timbres:cdc",
    "title": "La clé du caveau, 4e édition, 1872, n° 0383",
    "subtitle": null,
    "description": null,
    "composer": null,
    "metadata": [],
    "features": [],
    "sources": [],
    "files": [
        {
            "name": "score.xml",
            "url": "https://neuma.huma-num.fr//media/corpora/all/airs/timbres/cdc/0383/score.xml"
        },
        {
            "name": "mei.xml",
            "url": "https://neuma.huma-num.fr//media/corpora/all/airs/timbres/cdc/0383/mei.xml"
        }
    ]
}